hypermodern_python_cdavis/__init__.py
hypermodern_python_cdavis/console.py
hypermodern_python_cdavis/wikipedia.py
hypermodern_python_cdavis-1.0.3.dist-info/entry_points.txt
hypermodern_python_cdavis-1.0.3.dist-info/LICENSE
hypermodern_python_cdavis-1.0.3.dist-info/WHEEL
hypermodern_python_cdavis-1.0.3.dist-info/METADATA
hypermodern_python_cdavis-1.0.3.dist-info/RECORD
