Metadata-Version: 2.1
Name: hypermodern-python-cdavis
Version: 1.0.3
Summary: The hypermodern Python project
Home-page: https://github.com/cvdavis3/hypermodern-python-cdavis
License: MIT
Keywords: hypermodern
Author: Colin Davis
Author-email: cvdavis3@gmail.com
Requires-Python: >=3.7,<4.0
Classifier: License :: OSI Approved :: MIT License
Classifier: Programming Language :: Python :: 3
Classifier: Programming Language :: Python :: 3.7
Classifier: Programming Language :: Python :: 3.8
Requires-Dist: click (>=7.1.2,<8.0.0)
Requires-Dist: desert (>=2020.1.6,<2021.0.0)
Requires-Dist: importlib-metadata (>=2.0.0,<3.0.0); python_version < "3.8"
Requires-Dist: marshmallow (>=3.8.0,<4.0.0)
Requires-Dist: requests (>=2.24.0,<3.0.0)
Project-URL: Documentation, https://hypermodern-python-cdavis.readthedocs.io
Project-URL: Repository, https://github.com/cvdavis3/hypermodern-python-cdavis
